<annotation>
 <path>
  ErithacusRubecula0570.jpg
 </path>
 <source>
  <database>
   Unknown
  </database>
  <reviewresult>
  </reviewresult>
  <comment>
   <admin>
   </admin>
   <subord>
   </subord>
  </comment>
 </source>
 <size>
  <width>
   1024
  </width>
  <height>
   768
  </height>
  <depth>
   3
  </depth>
 </size>
 <segments>
  0
 </segments>
 <object>
  <name>
   Erithacus_Rubecula
  </name>
  <pose>
   Unspecified
  </pose>
  <truncated>
   0
  </truncated>
  <difficult>
   0
  </difficult>
  <bndbox>
   <xmin>
    385.2148403796376
   </xmin>
   <xmax>
    512.4417601380501
   </xmax>
   <ymin>
    347.22346850733385
   </ymin>
   <ymax>
    546.8990509059533
   </ymax>
  </bndbox>
 </object>
 <folder>
  dataset
 </folder>
 <filename>
  ErithacusRubecula0570.jpg
 </filename>
</annotation>