<annotation>
 <path>
  Periparus_ater_1063.jpg
 </path>
 <source>
  <database>
   Unknown
  </database>
  <reviewresult>
  </reviewresult>
  <comment>
   <admin>
   </admin>
   <subord>
   </subord>
  </comment>
 </source>
 <size>
  <width>
   560
  </width>
  <height>
   455
  </height>
  <depth>
   3
  </depth>
 </size>
 <segments>
  0
 </segments>
 <object>
  <name>
   Periparus_ater
  </name>
  <pose>
   Unspecified
  </pose>
  <truncated>
   0
  </truncated>
  <difficult>
   0
  </difficult>
  <bndbox>
   <xmin>
    176.62064998561976
   </xmin>
   <xmax>
    349.8792062122519
   </xmax>
   <ymin>
    161.2194420477423
   </ymin>
   <ymax>
    399.9079666379062
   </ymax>
  </bndbox>
 </object>
 <folder>
  dataset
 </folder>
 <filename>
  Periparus_ater_1063.jpg
 </filename>
</annotation>