<annotation>
 <path>
  Periparus_ater_1021.jpg
 </path>
 <source>
  <database>
   Unknown
  </database>
  <reviewresult>
  </reviewresult>
  <comment>
   <admin>
   </admin>
   <subord>
   </subord>
  </comment>
 </source>
 <size>
  <width>
   722
  </width>
  <height>
   1024
  </height>
  <depth>
   3
  </depth>
 </size>
 <segments>
  0
 </segments>
 <object>
  <name>
   Periparus_ater
  </name>
  <pose>
   Unspecified
  </pose>
  <truncated>
   0
  </truncated>
  <difficult>
   0
  </difficult>
  <bndbox>
   <xmin>
    23.438674360822834
   </xmin>
   <xmax>
    419.89627578137964
   </xmax>
   <ymin>
    408.52592250650423
   </ymin>
   <ymax>
    666.0689570416672
   </ymax>
  </bndbox>
 </object>
 <folder>
  dataset
 </folder>
 <filename>
  Periparus_ater_1021.jpg
 </filename>
</annotation>