<annotation>
 <path>
  Periparus_ater_1305.jpg
 </path>
 <source>
  <database>
   Unknown
  </database>
  <reviewresult>
  </reviewresult>
  <comment>
   <admin>
   </admin>
   <subord>
   </subord>
  </comment>
 </source>
 <size>
  <width>
   820
  </width>
  <height>
   1024
  </height>
  <depth>
   3
  </depth>
 </size>
 <segments>
  0
 </segments>
 <object>
  <name>
   Periparus_ater
  </name>
  <pose>
   Unspecified
  </pose>
  <truncated>
   0
  </truncated>
  <difficult>
   0
  </difficult>
  <bndbox>
   <xmin>
    217.3925798101812
   </xmin>
   <xmax>
    655.0762151279839
   </xmax>
   <ymin>
    341.62784009203335
   </ymin>
   <ymax>
    686.789761288467
   </ymax>
  </bndbox>
 </object>
 <folder>
  dataset
 </folder>
 <filename>
  Periparus_ater_1305.jpg
 </filename>
</annotation>