<annotation>
 <path>
  Pica_pica_628.jpg
 </path>
 <source>
  <database>
   Unknown
  </database>
  <reviewresult>
  </reviewresult>
  <comment>
   <admin>
   </admin>
   <subord>
   </subord>
  </comment>
 </source>
 <size>
  <width>
   1024
  </width>
  <height>
   683
  </height>
  <depth>
   3
  </depth>
 </size>
 <segments>
  0
 </segments>
 <object>
  <name>
   Pica_pica
  </name>
  <pose>
   Unspecified
  </pose>
  <truncated>
   0
  </truncated>
  <difficult>
   0
  </difficult>
  <bndbox>
   <xmin>
    425.96235637947296
   </xmin>
   <xmax>
    557.9642869592028
   </xmax>
   <ymin>
    270.81690781971975
   </ymin>
   <ymax>
    402.03401397249985
   </ymax>
  </bndbox>
 </object>
 <folder>
  dataset
 </folder>
 <filename>
  Pica_pica_628.jpg
 </filename>
</annotation>