<annotation>
 <path>
  Turdus_merula_680.jpg
 </path>
 <source>
  <database>
   Unknown
  </database>
  <reviewresult>
  </reviewresult>
  <comment>
   <admin>
   </admin>
   <subord>
   </subord>
  </comment>
 </source>
 <size>
  <width>
   1024
  </width>
  <height>
   768
  </height>
  <depth>
   3
  </depth>
 </size>
 <segments>
  0
 </segments>
 <object>
  <name>
   Turdus_merula
  </name>
  <pose>
   Unspecified
  </pose>
  <truncated>
   0
  </truncated>
  <difficult>
   0
  </difficult>
  <bndbox>
   <xmin>
    507.5431122648642
   </xmin>
   <xmax>
    868.6106970740201
   </xmax>
   <ymin>
    175.5860509549608
   </ymin>
   <ymax>
    517.8050832129046
   </ymax>
  </bndbox>
 </object>
 <folder>
  dataset
 </folder>
 <filename>
  Turdus_merula_680.jpg
 </filename>
</annotation>